geogr/__init__.py
geogr/geocodegr.py
geogr-0.0.4.dist-info/LICENSE
geogr-0.0.4.dist-info/METADATA
geogr-0.0.4.dist-info/WHEEL
geogr-0.0.4.dist-info/top_level.txt
geogr-0.0.4.dist-info/RECORD
