Metadata-Version: 2.1
Name: geogr
Version: 0.0.4
Summary: Package to process geographic data using the City of Grand Rapids ArcGIS system
Home-page: https://github.com/GRInnovation/geogr
Author: Zac Thiel
Author-email: digitalservices@grcity.us
License: UNKNOWN
Platform: UNKNOWN
Classifier: Programming Language :: Python :: 3
Classifier: License :: OSI Approved :: MIT License
Classifier: Operating System :: OS Independent
Requires-Python: >=3.7.6
